spritegrid/__init__.py
spritegrid/cli.py
spritegrid/detection.py
spritegrid/main.py
spritegrid/segmentation.py
spritegrid/utils.py
spritegrid-0.2.0.dist-info/METADATA
spritegrid-0.2.0.dist-info/WHEEL
spritegrid-0.2.0.dist-info/entry_points.txt
spritegrid-0.2.0.dist-info/licenses/LICENSE
spritegrid-0.2.0.dist-info/RECORD
