Metadata-Version: 2.4
Name: spritegrid
Version: 0.2.0
Summary: A command line tool for turning AI-generated pixel art into real pixel art.
License-File: LICENSE
Requires-Python: >=3.9
Requires-Dist: matplotlib>=3.10.1
Requires-Dist: opencv-python>=4.11.0.86
Requires-Dist: pillow>=11.1.0
Requires-Dist: requests>=2.32.3
Requires-Dist: scikit-learn>=1.6.1
Requires-Dist: scipy>=1.15.2
